[
    {
        "song": "Bite Me",
        "artist": "ENHYPEN"
    },
    {
        "song": "Ikarosz",
        "artist": "Elef\u00e1nt"
    },
    {
        "song": "Ikarosz",
        "artist": "Elef\u00e1nt"
    },
    {
        "song": "Jeffer Drive",
        "artist": "$uicideboy$"
    },
    {
        "song": "Whatever Floats Your Boat Will Definitely Sink My Ship",
        "artist": "$uicideboy$"
    },
    {
        "song": "Whatever Floats Your Boat Will Definitely Sink My Ship",
        "artist": "$uicideboy$"
    },
    {
        "song": "ponyvareg\u00e9ny",
        "artist": "gyuris"
    },
    {
        "song": "BUTA",
        "artist": "Elef\u00e1nt"
    },
    {
        "song": "Lelt\u00e1r",
        "artist": "Csaknekedkisl\u00e1ny"
    },
    {
        "song": "Sanctuary",
        "artist": "Joji"
    },
    {
        "song": "I've Seen Footage",
        "artist": "Death Grips"
    },
    {
        "song": "A SZOB\u00c1BAN VAN 1 PEDOFIL",
        "artist": "Lil Kubik A Creeper"
    },
    {
        "song": "Mit sem \u00e9rdekel",
        "artist": "Carson Coma"
    },
    {
        "song": "NATION ETERNAL",
        "artist": "Lil Darkie"
    },
    {
        "song": "k\u00f6b\u00e1ny\u00e6",
        "artist": "Azahriah"
    },
    {
        "song": "FELEJT\u0150",
        "artist": "Kr\u00fabi"
    },
    {
        "song": "FELEJT\u0150",
        "artist": "Kr\u00fabi"
    },
    {
        "song": "SEMMI",
        "artist": "Elef\u00e1nt"
    },
    {
        "song": "COLOSSAL CONFLICT",
        "artist": "Lil Darkie"
    },
    {
        "song": "Zuhanok",
        "artist": "4ma"
    },
    {
        "song": "PREACHER MAN",
        "artist": "Ye"
    },
    {
        "song": "didnt buy the beat",
        "artist": "Stunnaboi Jay"
    },
    {
        "song": "DAMN",
        "artist": "Ye"
    },
    {
        "song": "Ya Ight",
        "artist": "Destroy Lonely"
    },
    {
        "song": "I Am Pibble, Wash Mah Belleh",
        "artist": "Ryder Sirmons"
    },
    {
        "song": "National Treasures",
        "artist": "Drake"
    },
    {
        "song": "Magamat szeretem m\u00e1r",
        "artist": "H\u0171v\u00f6s"
    },
    {
        "song": "423",
        "artist": "H\u0171v\u00f6s"
    },
    {
        "song": "plusz egy (+1)",
        "artist": "Carson Coma"
    },
    {
        "song": "SEMMI",
        "artist": "Elef\u00e1nt"
    },
    {
        "song": "BALY",
        "artist": "Elef\u00e1nt"
    },
    {
        "song": "BUTA",
        "artist": "Elef\u00e1nt"
    },
    {
        "song": "SZER\u00c1F",
        "artist": "Elef\u00e1nt"
    },
    {
        "song": "POP",
        "artist": "Beton.Hofi"
    },
    {
        "song": "POP",
        "artist": "Beton.Hofi"
    },
    {
        "song": "POP",
        "artist": "Beton.Hofi"
    },
    {
        "song": "BAGIRA",
        "artist": "Beton.Hofi"
    },
    {
        "song": "POP",
        "artist": "Beton.Hofi"
    },
    {
        "song": "DOH\u00c1NYBOLT",
        "artist": "Beton.Hofi"
    },
    {
        "song": "444888",
        "artist": "Elef\u00e1nt"
    },
    {
        "song": "h\u00f3angyal",
        "artist": "gyuris"
    },
    {
        "song": "Kocsiban \u00fcl",
        "artist": "Wavy"
    },
    {
        "song": "Kocsiban \u00fcl",
        "artist": "Wavy"
    },
    {
        "song": "Kocsiban \u00fcl",
        "artist": "Wavy"
    },
    {
        "song": "ponyvareg\u00e9ny",
        "artist": "gyuris"
    },
    {
        "song": "DADDY",
        "artist": "Mirror Glimpse"
    },
    {
        "song": "B\u00c1MM 2",
        "artist": "Mirror Glimpse"
    },
    {
        "song": "B\u00c1MM 2",
        "artist": "Mirror Glimpse"
    },
    {
        "song": "PANASONIC",
        "artist": "Beton.Hofi"
    },
    {
        "song": "DISNEY",
        "artist": "Beton.Hofi"
    }
]